{
  "displayName": "SJK(T) Connect — Egress by Route/UA",
  "etag": "49f2f577bfea91bed5ad4e4b98da5893",
  "mosaicLayout": {
    "columns": 12,
    "tiles": [
      {
        "height": 4,
        "widget": {
          "title": "API egress by route (top 10)",
          "xyChart": {
            "dataSets": [
              {
                "plotType": "STACKED_BAR",
                "targetAxis": "Y1",
                "timeSeriesQuery": {
                  "timeSeriesQueryLanguage": "fetch cloud_run_revision::logging.googleapis.com/user/sjktconnect_api_egress_per_route\n| align delta(1h)\n| every 1h\n| group_by [metric.route], sum(value)\n| top 10"
                }
              }
            ],
            "yAxis": {"label": "bytes/hr", "scale": "LINEAR"}
          }
        },
        "width": 6
      },
      {
        "height": 4,
        "widget": {
          "title": "Web egress by route (top 10)",
          "xyChart": {
            "dataSets": [
              {
                "plotType": "STACKED_BAR",
                "targetAxis": "Y1",
                "timeSeriesQuery": {
                  "timeSeriesQueryLanguage": "fetch cloud_run_revision::logging.googleapis.com/user/sjktconnect_web_egress_per_route\n| align delta(1h)\n| every 1h\n| group_by [metric.route], sum(value)\n| top 10"
                }
              }
            ],
            "yAxis": {"label": "bytes/hr", "scale": "LINEAR"}
          }
        },
        "width": 6,
        "xPos": 6
      },
      {
        "height": 4,
        "widget": {
          "title": "API egress by User-Agent (bot detection, top 10)",
          "xyChart": {
            "dataSets": [
              {
                "plotType": "STACKED_BAR",
                "targetAxis": "Y1",
                "timeSeriesQuery": {
                  "timeSeriesQueryLanguage": "fetch cloud_run_revision::logging.googleapis.com/user/sjktconnect_api_egress_per_route\n| align delta(1h)\n| every 1h\n| group_by [metric.user_agent], sum(value)\n| top 10"
                }
              }
            ],
            "yAxis": {"label": "bytes/hr", "scale": "LINEAR"}
          }
        },
        "width": 6,
        "yPos": 4
      },
      {
        "height": 4,
        "widget": {
          "title": "Web egress by User-Agent (bot detection, top 10)",
          "xyChart": {
            "dataSets": [
              {
                "plotType": "STACKED_BAR",
                "targetAxis": "Y1",
                "timeSeriesQuery": {
                  "timeSeriesQueryLanguage": "fetch cloud_run_revision::logging.googleapis.com/user/sjktconnect_web_egress_per_route\n| align delta(1h)\n| every 1h\n| group_by [metric.user_agent], sum(value)\n| top 10"
                }
              }
            ],
            "yAxis": {"label": "bytes/hr", "scale": "LINEAR"}
          }
        },
        "width": 6,
        "xPos": 6,
        "yPos": 4
      }
    ]
  },
  "name": "projects/748286712183/dashboards/f1722366-2df9-4446-9941-7cda5c019615"
}
